qglmm/__init__.py
qglmm/qglmm.py
qglmm-0.1.1.dist-info/licenses/LICENSE
qglmm-0.1.1.dist-info/METADATA
qglmm-0.1.1.dist-info/WHEEL
qglmm-0.1.1.dist-info/top_level.txt
qglmm-0.1.1.dist-info/RECORD
