Metadata-Version: 2.4
Name: qglmm
Version: 0.1.1
Summary: Quick Generalized Linear Mixed Models
Author-email: Ali Akbari <alek0991@gmail.com>
License: MIT License
Requires-Python: >=3.8
License-File: LICENSE
Requires-Dist: pandas
Requires-Dist: numpy
Requires-Dist: statsmodels
Requires-Dist: scipy
Dynamic: license-file
